<?xml version="1.0" encoding="UTF-8"?>
<mutaties op="archief/waardelijsten 2.1.0.xml" datum="2022-01-31">
  <mutatie type="vervang" xpath="waardelijsten//waarde[uri='http://standaarden.omgevingswet.overheid.nl/typenorm/id/concept/AantalWinkels']/toelichting">
    <toelichting>[Toelichting]</toelichting>
  </mutatie>
  <mutatie type="vervang" xpath="waardelijsten/versie">
    <versie>2.1.1</versie>
  </mutatie>
  <mutatie type="vervang" xpath="waardelijsten/publicatiedatum">
    <publicatiedatum>2022-01-31</publicatiedatum>
  </mutatie>
  <mutatie type="verwijder" xpath="waardelijsten//waarde[uri='http://standaarden.omgevingswet.overheid.nl/typenorm/id/concept/AantalBezoekers']"/>
</mutaties>